{
  "Gasket": [
    {
      "Material": "Резина по ГОСТ 7338 с твердостью по Шору А до 65 едениц",
      "m": 0.5,
      "qobj": 2.0,
      "q_d": 18.0,
      "Kobj": 0.04
    },
    {
      "Material": "Резина по ГОСТ 7338 с твердостью по Шору А более 65 едениц",
      "m": 1.0,
      "qobj": 4.0,
      "q_d": 20.0,
      "Kobj": 0.09
    },
    {
      "Material": "Паронит по ГОСТ 481 при толщине не более 2—3 мм",
      "m": 2.5,
      "qobj": 20.0,
      "q_d": 130.0,
      "Kobj": 0.9,
      "Ep": 2000
    },
    {
      "Material": "Паронит по ГОСТ 481 при толщине не более 2—3 мм, для сред с высокой проницающей способностью (водород, гелий, легкие нефтепродукты, сжиженные газы)",
      "m": 2.5,
      "qobj": 35.0,
      "q_d": 130.0,
      "Kobj": 0.9,
      "Ep": 2000
    },
    {
      "Material": "Картон асбестовый по ГОСТ 2850 при толщине 1—3 мм",
      "m": 2.5,
      "qobj": 20.0,
      "q_d": 130.0,
      "Kobj": 0.9,
      "Ep": 2000
    },
    {
      "Material": "Фторопласт 4 при толщине 1—3 мм",
      "m": 2.5,
      "qobj": 10.0,
      "q_d": 40.0,
      "Kobj": 1.0,
      "Ep": 2000
    },
    {
      "Material": "Терморасширенный графитовый материал (типа «Графлекс») с обтюратором",
      "m": 2.0,
      "qobj": 4.0,
      "q_d": 200.0,
      "Kobj": 1.0,
      "Ep": 2000
    },
    {
      "Material": "Терморасширенный графитовый материал (типа «Графлекс») без обтюратора hп=2мм",
      "m": 2.5,
      "qobj": 4.0,
      "q_d": 120.0,
      "Kobj": 1.0,
      "Ep": 2000
    },
    {
      "Material": "Терморасширенный графитовый материал (типа «Графлекс») без обтюратора hп=3мм",
      "m": 2.5,
      "qobj": 4.0,
      "q_d": 100.0,
      "Kobj": 1.0,
      "Ep": 2000
    },
    {
      "Material": "Аллюминий марки АД по ГОСТ 21631",
      "m": 4.0,
      "qobj": 60.0
    },
    {
      "Material": "Латунь марки Л63 по ГОСТ 2208",
      "m": 4.75,
      "qobj": 90.0
    },
    {
      "Material": "Сталь марки 05кп по ГОСТ 9045",
      "m": 5.5,
      "qobj": 125.0
    }
  ]
}