[
	{
		"Name": [ "35", "40" ],
		"Values": {
			"20": 130.0,
			"100": 126.0,
			"200": 120.0,
			"250": 107,
			"300": 97.0,
			"350": 86.0,
			"375": 80.0,
			"400": 75.0,
			"425": 68.0
		}
	},
	{
		"Name": [ "12Х18Н10Т", "10Х17Н13М2Т" ],
		"Values": {
			"20": 110.0,
			"100": 105.0,
			"200": 98.0,
			"250": 95.0,
			"300": 90.0,
			"350": 86.0,
			"375": 85.0,
			"400": 83.0,
			"425": 82.0,
			"450": 80.0,
			"475": 79.0,
			"500": 78.0,
			"510": 75.0,
			"520": 73.0,
			"530": 70.0,
			"540": 65.0,
			"550": 63.0,
			"600": 56.0
		}
	},
	{
		"Name": [ "45Х14Н14В2М" ],
		"Values": {
			"20": 160.0,
			"100": 150.0,
			"200": 150.0,
			"250": 144.0,
			"300": 139.0,
			"350": 128.0,
			"375": 128.0,
			"400": 128.0,
			"425": 125.0,
			"450": 123.0,
			"475": 120.0,
			"500": 118.0,
			"510": 117.0,
			"520": 116.0,
			"530": 115.0,
			"540": 114.0,
			"550": 113.0
		}
	},
  {
    "Name": [ "14Х17Н2" ],
		"Values": {
			"20": 232.0,
			"100": 230.0,
			"200": 220.0,
			"250": 218.0,
			"300": 209.0,
			"350": 207.0
		}
  }
]

	

